test/__init__.py
test/test_sanity.py
watson_streaming/__init__.py
watson_streaming/transcriber.py
watson_streaming/utilities.py
watson_streaming-0.0.13.dist-info/LICENSE
watson_streaming-0.0.13.dist-info/METADATA
watson_streaming-0.0.13.dist-info/WHEEL
watson_streaming-0.0.13.dist-info/top_level.txt
watson_streaming-0.0.13.dist-info/RECORD
