Metadata-Version: 2.1
Name: watson-streaming
Version: 0.0.13
Summary: Speech to text transcription in real-time using IBM Watson
Home-page: https://github.com/Nagasaki45/watson-streaming
Author: Tom Gurion
Author-email: nagasaki45@gmail.com
License: UNKNOWN
Keywords: ibm watson stt asr
Platform: UNKNOWN
Classifier: Development Status :: 3 - Alpha
Classifier: Intended Audience :: Developers
Classifier: Intended Audience :: Science/Research
Classifier: Topic :: Multimedia :: Sound/Audio :: Capture/Recording
Classifier: Topic :: Multimedia :: Sound/Audio :: Speech
Classifier: Topic :: Scientific/Engineering :: Human Machine Interfaces
Classifier: License :: OSI Approved :: MIT License
Classifier: Programming Language :: Python :: 2
Classifier: Programming Language :: Python :: 2.7
Classifier: Programming Language :: Python :: 3
Classifier: Programming Language :: Python :: 3.4
Classifier: Programming Language :: Python :: 3.5
Classifier: Programming Language :: Python :: 3.6
Requires-Dist: requests
Requires-Dist: sounddevice
Requires-Dist: websocket-client
Requires-Dist: fluteline
